ConcurrentExecutionEnhanced/ConcurrentExecutionEnhanced.py
ConcurrentExecutionEnhanced/__init__.py
concurrentexecutionenhanced-0.1.0.dist-info/licenses/LICENSE
concurrentexecutionenhanced-0.1.0.dist-info/METADATA
concurrentexecutionenhanced-0.1.0.dist-info/WHEEL
concurrentexecutionenhanced-0.1.0.dist-info/top_level.txt
concurrentexecutionenhanced-0.1.0.dist-info/RECORD
