Metadata-Version: 2.4
Name: ConcurrentExecutionEnhanced
Version: 0.1.0
License: MIT License
Project-URL: Homepage, https://github.com/twh970723/ConcurrentExecutionEnhanced
Requires-Python: >=3.11
License-File: LICENSE
Dynamic: license-file
